README.md
setup.py
treeplotter/__init__.py
treeplotter/cli.py
treeplotter/installation_assistant.py
treeplotter/plotter.py
treeplotter/style.py
treeplotter/tree.py
treeplotter.egg-info/PKG-INFO
treeplotter.egg-info/SOURCES.txt
treeplotter.egg-info/dependency_links.txt
treeplotter.egg-info/entry_points.txt
treeplotter.egg-info/requires.txt
treeplotter.egg-info/top_level.txt