Metadata-Version: 2.1
Name: treeplotter
Version: 0.4.0
Summary: Python package for tree plotting.
Home-page: https://github.com/Luke-Poeppel/treeplotter
Author: Luke Poeppel
Author-email: luke.poeppel@gmail.com
License: UNKNOWN
Platform: UNKNOWN
Classifier: Programming Language :: Python :: 3
Classifier: License :: OSI Approved :: MIT License
Classifier: Operating System :: OS Independent
Requires-Python: >=3.7
